{
    "bg": "https://img.nbc.com/sites/nbcunbc/files/scet/photos/22/1217/006.jpg?impolicy=nbc_com&imwidth=1080&imdensity=1" ,
    "bgQuiz" : "https://imagesvc.meredithcorp.io/v3/mm/image?url=https%3A%2F%2Fstatic.onecms.io%2Fwp-content%2Fuploads%2Fsites%2F20%2F2020%2F04%2F03%2Fzoom-4.jpg",
    "title": "Quiz The Office",
    "description": "Teste os seus conhecimentos sobre a série!",
    "questions": [
      {
        "image": "https://media.giphy.com/media/xUOxf3yDKCuwpOlT3i/giphy.gif",
        "title": "Pergunta 1",
        "description": "Desc 1",
        "answer": 2,
        "alternatives": [
          "alt 1",
          "alt2",
          "alt3",
          "alt4"
        ]
      },
      {
        "image": "https://media.giphy.com/media/13FrpeVH09Zrb2/giphy.gif",
        "title": "Pergunta 2",
        "description": "Desc 2",
        "answer": 2,
        "alternatives": [
          "alt 1",
          "alt2",
          "alt3"
        ]
      },
      {
        "image": "https://media.giphy.com/media/13FrpeVH09Zrb2/giphy.gif",
        "title": "Pergunta 3",
        "description": "Desc 3",
        "answer": 2,
        "alternatives": [
          "alt 1",
          "alt2",
          "alt3",
          "alt4"
        ]
      },
      {
        "image": "https://media.giphy.com/media/13FrpeVH09Zrb2/giphy.gif",
        "title": "Pergunta 4",
        "description": "Desc 4",
        "answer": 2,
        "alternatives": [
          "alt 1",
          "alt2",
          "alt3",
          "alt4"
        ]
      }
    ],
    "external": [
      ""
    ],
    "theme": {
      "colors": {
        "textheader" : "#E9ECED",
        "primary": "#0C2F57",
        "secondary": "#FFC300",
        "mainBg": "#DCDBD9",
        "contrastText": "#4A4948",
        "wrong": "#FF5722",
        "success": "#4CAF50"
      },
      "borderRadius": "4px"
    }
  }